{
  "annotations": {
    "list": [
      {
        "builtIn": 1,
        "datasource": {
          "type": "datasource",
          "uid": "grafana"
        },
        "enable": true,
        "hide": true,
        "iconColor": "rgba(0, 211, 255, 1)",
        "name": "Annotations & Alerts",
        "type": "dashboard"
      }
    ]
  },
  "description": "Loki version 2 showcase using JSON NGINX access logs.",
  "editable": true,
  "fiscalYearStartMonth": 0,
  "gnetId": 13740,
  "graphTooltip": 0,
  "id": 1,
  "links": [],
  "liveNow": false,
  "panels": [
    {
      "collapsed": false,
      "datasource": {
        "type": "loki",
        "uid": "cdgce71h6yz28c"
      },
      "gridPos": {
        "h": 1,
        "w": 24,
        "x": 0,
        "y": 0
      },
      "id": 24,
      "panels": [],
      "targets": [
        {
          "datasource": {
            "type": "loki",
            "uid": "cdgce71h6yz28c"
          },
          "refId": "A"
        }
      ],
      "title": "KPI's",
      "type": "row"
    },
    {
      "datasource": {
        "type": "loki",
        "uid": "cdgce71h6yz28c"
      },
      "description": "",
      "fieldConfig": {
        "defaults": {
          "mappings": [],
          "thresholds": {
            "mode": "absolute",
            "steps": [
              {
                "color": "purple",
                "value": null
              }
            ]
          },
          "unit": "short"
        },
        "overrides": []
      },
      "gridPos": {
        "h": 4,
        "w": 6,
        "x": 0,
        "y": 1
      },
      "id": 4,
      "interval": "30s",
      "options": {
        "colorMode": "background",
        "graphMode": "area",
        "justifyMode": "center",
        "orientation": "auto",
        "reduceOptions": {
          "calcs": [],
          "fields": "",
          "values": true
        },
        "showPercentChange": false,
        "textMode": "value",
        "wideLayout": true
      },
      "pluginVersion": "10.4.0",
      "targets": [
        {
          "datasource": {
            "type": "loki",
            "uid": "cdgce71h6yz28c"
          },
          "editorMode": "builder",
          "expr": "sum by(job) (count_over_time({job=\"fluentbit\"} [$__auto]))",
          "legendFormat": "",
          "queryType": "instant",
          "refId": "A"
        }
      ],
      "timeFrom": "24h",
      "title": "Total requests  ",
      "type": "stat"
    },
    {
      "datasource": {
        "type": "loki",
        "uid": "cdgce71h6yz28c"
      },
      "description": "",
      "fieldConfig": {
        "defaults": {
          "mappings": [],
          "thresholds": {
            "mode": "absolute",
            "steps": [
              {
                "color": "light-blue",
                "value": null
              }
            ]
          },
          "unit": "short"
        },
        "overrides": []
      },
      "gridPos": {
        "h": 8,
        "w": 9,
        "x": 6,
        "y": 1
      },
      "id": 5,
      "interval": "30s",
      "options": {
        "colorMode": "background",
        "graphMode": "area",
        "justifyMode": "auto",
        "orientation": "auto",
        "reduceOptions": {
          "calcs": [
            "sum"
          ],
          "fields": "",
          "values": false
        },
        "showPercentChange": false,
        "textMode": "auto",
        "wideLayout": true
      },
      "pluginVersion": "10.4.0",
      "targets": [
        {
          "datasource": {
            "type": "loki",
            "uid": "cdgce71h6yz28c"
          },
          "editorMode": "builder",
          "expr": "sum by(status) (count_over_time({job=\"fluentbit\"} | json status | __error__=`` [$__auto]))",
          "legendFormat": "HTTP Status: {{status}}",
          "queryType": "range",
          "refId": "A"
        }
      ],
      "title": "Requests per HTTP status code",
      "type": "stat"
    },
    {
      "datasource": {
        "type": "loki",
        "uid": "cdgce71h6yz28c"
      },
      "description": "",
      "fieldConfig": {
        "defaults": {
          "mappings": [],
          "max": 100,
          "min": 0,
          "thresholds": {
            "mode": "absolute",
            "steps": [
              {
                "color": "purple",
                "value": null
              },
              {
                "color": "red",
                "value": 80
              }
            ]
          },
          "unit": "percent"
        },
        "overrides": []
      },
      "gridPos": {
        "h": 4,
        "w": 5,
        "x": 15,
        "y": 1
      },
      "id": 19,
      "maxDataPoints": 1,
      "options": {
        "colorMode": "background",
        "graphMode": "none",
        "justifyMode": "center",
        "orientation": "auto",
        "reduceOptions": {
          "calcs": [
            "mean"
          ],
          "fields": "",
          "values": false
        },
        "showPercentChange": false,
        "textMode": "value",
        "wideLayout": true
      },
      "pluginVersion": "10.4.0",
      "targets": [
        {
          "datasource": {
            "type": "loki",
            "uid": "cdgce71h6yz28c"
          },
          "editorMode": "builder",
          "expr": "(sum(rate({job=\"fluentbit\"} | json | status >= 500 | __error__=`` [$__auto])) / 100) / sum(rate({job=\"fluentbit\"} | json | __error__=`` [$__auto]))",
          "legendFormat": "",
          "queryType": "range",
          "refId": "A"
        }
      ],
      "title": "% of 5xx requests ",
      "type": "stat"
    },
    {
      "datasource": {
        "type": "loki",
        "uid": "cdgce71h6yz28c"
      },
      "description": "",
      "fieldConfig": {
        "defaults": {
          "mappings": [],
          "max": 100,
          "min": 0,
          "thresholds": {
            "mode": "absolute",
            "steps": [
              {
                "color": "purple",
                "value": null
              }
            ]
          },
          "unit": "percent"
        },
        "overrides": []
      },
      "gridPos": {
        "h": 4,
        "w": 4,
        "x": 20,
        "y": 1
      },
      "id": 18,
      "interval": "10m",
      "maxDataPoints": 1,
      "options": {
        "colorMode": "background",
        "graphMode": "none",
        "justifyMode": "auto",
        "orientation": "auto",
        "reduceOptions": {
          "calcs": [
            "last"
          ],
          "fields": "",
          "values": false
        },
        "showPercentChange": false,
        "textMode": "value",
        "wideLayout": true
      },
      "pluginVersion": "10.4.0",
      "targets": [
        {
          "datasource": {
            "type": "loki",
            "uid": "cdgce71h6yz28c"
          },
          "editorMode": "builder",
          "expr": "sum(rate({job=\"fluentbit\"} |= `Googlebot` [$__auto])) / sum(rate({job=\"fluentbit\"} != `Googlebot` [$__auto])) / 100",
          "legendFormat": "",
          "queryType": "range",
          "refId": "A"
        }
      ],
      "title": "% of requests by Googlebot",
      "type": "stat"
    },
    {
      "datasource": {
        "type": "loki",
        "uid": "cdgce71h6yz28c"
      },
      "description": "",
      "fieldConfig": {
        "defaults": {
          "mappings": [],
          "thresholds": {
            "mode": "absolute",
            "steps": [
              {
                "color": "purple",
                "value": null
              }
            ]
          }
        },
        "overrides": []
      },
      "gridPos": {
        "h": 4,
        "w": 6,
        "x": 0,
        "y": 5
      },
      "hideTimeOverride": false,
      "id": 22,
      "interval": "5m",
      "options": {
        "colorMode": "background",
        "graphMode": "none",
        "justifyMode": "auto",
        "orientation": "auto",
        "reduceOptions": {
          "calcs": [
            "mean"
          ],
          "fields": "",
          "values": false
        },
        "showPercentChange": false,
        "textMode": "value",
        "wideLayout": true
      },
      "pluginVersion": "10.4.0",
      "targets": [
        {
          "datasource": {
            "type": "loki",
            "uid": "cdgce71h6yz28c"
          },
          "editorMode": "builder",
          "expr": "count(sum by(http_x_forwarded_for) (count_over_time({job=\"fluentbit\"} | json http_x_forwarded_for | __error__=`` [5m])))",
          "legendFormat": "",
          "queryType": "range",
          "refId": "A"
        }
      ],
      "timeFrom": "5m",
      "title": "Users right now",
      "type": "stat"
    },
    {
      "datasource": {
        "type": "loki",
        "uid": "cdgce71h6yz28c"
      },
      "description": "",
      "fieldConfig": {
        "defaults": {
          "mappings": [],
          "thresholds": {
            "mode": "absolute",
            "steps": [
              {
                "color": "purple",
                "value": null
              }
            ]
          },
          "unit": "decbytes"
        },
        "overrides": []
      },
      "gridPos": {
        "h": 4,
        "w": 9,
        "x": 15,
        "y": 5
      },
      "id": 8,
      "interval": "10m",
      "options": {
        "colorMode": "background",
        "graphMode": "none",
        "justifyMode": "center",
        "orientation": "auto",
        "reduceOptions": {
          "calcs": [
            "sum"
          ],
          "fields": "",
          "values": false
        },
        "showPercentChange": false,
        "textMode": "value",
        "wideLayout": true
      },
      "pluginVersion": "10.4.0",
      "targets": [
        {
          "datasource": {
            "type": "loki",
            "uid": "cdgce71h6yz28c"
          },
          "editorMode": "builder",
          "expr": "sum by(job) (sum_over_time({job=\"fluentbit\"} | json status, body_bytes_sent | status = `200` | unwrap body_bytes_sent | __error__=`` [$__auto]))",
          "legendFormat": "Bytes sent",
          "queryType": "instant",
          "refId": "A"
        }
      ],
      "title": "Total Bytes Sent",
      "transformations": [
        {
          "id": "reduce",
          "options": {
            "reducers": [
              "sum"
            ]
          }
        },
        {
          "id": "organize",
          "options": {
            "excludeByName": {},
            "indexByName": {},
            "renameByName": {
              "Total": "Bytes Sent"
            }
          }
        }
      ],
      "type": "stat"
    },
    {
      "datasource": {
        "type": "loki",
        "uid": "cdgce71h6yz28c"
      },
      "description": "",
      "gridPos": {
        "h": 9,
        "w": 10,
        "x": 0,
        "y": 9
      },
      "id": 11,
      "options": {
        "dedupStrategy": "none",
        "enableLogDetails": true,
        "prettifyLogMessage": false,
        "showCommonLabels": false,
        "showLabels": false,
        "showTime": false,
        "sortOrder": "Descending",
        "wrapLogMessage": false
      },
      "targets": [
        {
          "datasource": {
            "type": "loki",
            "uid": "cdgce71h6yz28c"
          },
          "editorMode": "builder",
          "expr": "{job=\"fluentbit\"} | json request_uri, status, request_method | line_format `➡️ {{.request_method}} {{.request_uri}} with HTTP status: {{.status}} `",
          "legendFormat": "",
          "maxLines": 100,
          "queryType": "range",
          "refId": "A"
        }
      ],
      "title": "Recent requests",
      "type": "logs"
    },
    {
      "datasource": {
        "type": "loki",
        "uid": "cdgce71h6yz28c"
      },
      "description": "",
      "fieldConfig": {
        "defaults": {
          "color": {
            "fixedColor": "blue",
            "mode": "fixed"
          },
          "custom": {
            "axisBorderShow": false,
            "axisCenteredZero": false,
            "axisColorMode": "text",
            "axisLabel": "",
            "axisPlacement": "auto",
            "barAlignment": 0,
            "drawStyle": "line",
            "fillOpacity": 100,
            "gradientMode": "hue",
            "hideFrom": {
              "legend": false,
              "tooltip": false,
              "viz": false
            },
            "insertNulls": false,
            "lineInterpolation": "smooth",
            "lineStyle": {
              "fill": "solid"
            },
            "lineWidth": 1,
            "pointSize": 5,
            "scaleDistribution": {
              "type": "linear"
            },
            "showPoints": "never",
            "spanNulls": false,
            "stacking": {
              "group": "A",
              "mode": "none"
            },
            "thresholdsStyle": {
              "mode": "off"
            }
          },
          "fieldMinMax": false,
          "mappings": [],
          "thresholds": {
            "mode": "absolute",
            "steps": [
              {
                "color": "blue",
                "value": null
              }
            ]
          },
          "unit": "reqps"
        },
        "overrides": []
      },
      "gridPos": {
        "h": 9,
        "w": 8,
        "x": 10,
        "y": 9
      },
      "id": 30,
      "interval": "30s",
      "options": {
        "legend": {
          "calcs": [],
          "displayMode": "list",
          "placement": "bottom",
          "showLegend": true
        },
        "tooltip": {
          "mode": "single",
          "sort": "none"
        }
      },
      "pluginVersion": "10.4.0",
      "targets": [
        {
          "datasource": {
            "type": "loki",
            "uid": "cdgce71h6yz28c"
          },
          "editorMode": "builder",
          "expr": "rate({job=\"fluentbit\"} | json job [$__auto])",
          "legendFormat": "Requests Per Second",
          "queryType": "range",
          "refId": "A"
        }
      ],
      "title": "Requests Per Second",
      "type": "timeseries"
    },
    {
      "datasource": {
        "type": "loki",
        "uid": "cdgce71h6yz28c"
      },
      "description": "These are values that were in HIT or STALE meaning the cached value got returned.",
      "fieldConfig": {
        "defaults": {
          "mappings": [],
          "thresholds": {
            "mode": "absolute",
            "steps": [
              {
                "color": "purple",
                "value": null
              }
            ]
          },
          "unit": "decbytes"
        },
        "overrides": []
      },
      "gridPos": {
        "h": 4,
        "w": 6,
        "x": 18,
        "y": 9
      },
      "id": 29,
      "interval": "10m",
      "options": {
        "colorMode": "background",
        "graphMode": "none",
        "justifyMode": "center",
        "orientation": "auto",
        "reduceOptions": {
          "calcs": [
            "sum"
          ],
          "fields": "",
          "values": false
        },
        "showPercentChange": false,
        "textMode": "value",
        "wideLayout": true
      },
      "pluginVersion": "10.4.0",
      "targets": [
        {
          "datasource": {
            "type": "loki",
            "uid": "cdgce71h6yz28c"
          },
          "editorMode": "builder",
          "expr": "sum by(job) (sum_over_time({job=\"fluentbit\"} | json upstream_cache_status, body_bytes_sent | upstream_cache_status = `HIT` | unwrap body_bytes_sent | __error__=`` [$__auto]))",
          "legendFormat": "Bytes sent",
          "queryType": "instant",
          "refId": "A"
        }
      ],
      "title": "Cached Bytes Sent",
      "transformations": [
        {
          "id": "reduce",
          "options": {
            "reducers": [
              "sum"
            ]
          }
        },
        {
          "id": "organize",
          "options": {
            "excludeByName": {},
            "indexByName": {},
            "renameByName": {
              "Total": "Bytes Sent"
            }
          }
        }
      ],
      "type": "stat"
    },
    {
      "collapsed": false,
      "datasource": {
        "type": "loki",
        "uid": "cdgce71h6yz28c"
      },
      "gridPos": {
        "h": 1,
        "w": 24,
        "x": 0,
        "y": 18
      },
      "id": 26,
      "panels": [],
      "targets": [
        {
          "datasource": {
            "type": "loki",
            "uid": "cdgce71h6yz28c"
          },
          "refId": "A"
        }
      ],
      "title": "Request statistics over time",
      "type": "row"
    },
    {
      "datasource": {
        "type": "loki",
        "uid": "cdgce71h6yz28c"
      },
      "description": "",
      "fieldConfig": {
        "defaults": {
          "color": {
            "mode": "palette-classic"
          },
          "custom": {
            "axisBorderShow": false,
            "axisCenteredZero": false,
            "axisColorMode": "text",
            "axisLabel": "",
            "axisPlacement": "auto",
            "barAlignment": 0,
            "drawStyle": "line",
            "fillOpacity": 100,
            "gradientMode": "opacity",
            "hideFrom": {
              "legend": false,
              "tooltip": false,
              "viz": false
            },
            "insertNulls": false,
            "lineInterpolation": "smooth",
            "lineWidth": 1,
            "pointSize": 5,
            "scaleDistribution": {
              "type": "linear"
            },
            "showPoints": "never",
            "spanNulls": false,
            "stacking": {
              "group": "A",
              "mode": "none"
            },
            "thresholdsStyle": {
              "mode": "area"
            }
          },
          "mappings": [],
          "thresholds": {
            "mode": "absolute",
            "steps": [
              {
                "color": "green",
                "value": null
              },
              {
                "color": "#EAB839",
                "value": 0.2
              },
              {
                "color": "red",
                "value": 0.3
              }
            ]
          },
          "unit": "s"
        },
        "overrides": [
          {
            "matcher": {
              "id": "byName",
              "options": "95th percentile"
            },
            "properties": [
              {
                "id": "color",
                "value": {
                  "fixedColor": "blue",
                  "mode": "fixed"
                }
              }
            ]
          },
          {
            "matcher": {
              "id": "byName",
              "options": "max latency"
            },
            "properties": [
              {
                "id": "color",
                "value": {
                  "fixedColor": "super-light-blue",
                  "mode": "fixed"
                }
              }
            ]
          },
          {
            "matcher": {
              "id": "byName",
              "options": "max latency"
            },
            "properties": [
              {
                "id": "custom.fillOpacity",
                "value": 30
              }
            ]
          }
        ]
      },
      "gridPos": {
        "h": 9,
        "w": 7,
        "x": 0,
        "y": 19
      },
      "id": 16,
      "interval": "30s",
      "options": {
        "legend": {
          "calcs": [],
          "displayMode": "list",
          "placement": "bottom",
          "showLegend": true
        },
        "tooltip": {
          "mode": "multi",
          "sort": "none"
        }
      },
      "pluginVersion": "10.4.0",
      "targets": [
        {
          "datasource": {
            "type": "loki",
            "uid": "cdgce71h6yz28c"
          },
          "editorMode": "builder",
          "expr": "quantile_over_time(0.95, {job=\"fluentbit\"} | json | unwrap request_time | __error__=`` [$__auto]) by (job)",
          "legendFormat": "95th percentile",
          "queryType": "range",
          "refId": "C"
        },
        {
          "datasource": {
            "type": "loki",
            "uid": "cdgce71h6yz28c"
          },
          "editorMode": "builder",
          "expr": "max by(job) (max_over_time({job=\"fluentbit\"} | json | unwrap request_time | __error__=`` [$__auto]))",
          "legendFormat": "max latency",
          "queryType": "range",
          "refId": "D"
        }
      ],
      "title": "95th percentile of Request Time (upstream)",
      "type": "timeseries"
    },
    {
      "datasource": {
        "type": "loki",
        "uid": "cdgce71h6yz28c"
      },
      "description": "",
      "fieldConfig": {
        "defaults": {
          "color": {
            "mode": "palette-classic"
          },
          "custom": {
            "axisBorderShow": false,
            "axisCenteredZero": false,
            "axisColorMode": "text",
            "axisLabel": "",
            "axisPlacement": "auto",
            "barAlignment": 0,
            "drawStyle": "line",
            "fillOpacity": 39,
            "gradientMode": "hue",
            "hideFrom": {
              "legend": false,
              "tooltip": false,
              "viz": false
            },
            "insertNulls": false,
            "lineInterpolation": "smooth",
            "lineWidth": 1,
            "pointSize": 5,
            "scaleDistribution": {
              "log": 2,
              "type": "log"
            },
            "showPoints": "never",
            "spanNulls": false,
            "stacking": {
              "group": "A",
              "mode": "none"
            },
            "thresholdsStyle": {
              "mode": "off"
            }
          },
          "decimals": 0,
          "mappings": [],
          "thresholds": {
            "mode": "absolute",
            "steps": [
              {
                "color": "green",
                "value": null
              },
              {
                "color": "red",
                "value": 80
              }
            ]
          },
          "unit": "short"
        },
        "overrides": [
          {
            "matcher": {
              "id": "byName",
              "options": "HTTP Status 200"
            },
            "properties": [
              {
                "id": "color",
                "value": {
                  "fixedColor": "dark-blue",
                  "mode": "fixed"
                }
              }
            ]
          },
          {
            "matcher": {
              "id": "byName",
              "options": "{statuscode=\"404\"} 404"
            },
            "properties": [
              {
                "id": "color",
                "value": {
                  "fixedColor": "semi-dark-purple",
                  "mode": "fixed"
                }
              }
            ]
          },
          {
            "matcher": {
              "id": "byName",
              "options": "{statuscode=\"500\"} 500"
            },
            "properties": [
              {
                "id": "color",
                "value": {
                  "fixedColor": "dark-red",
                  "mode": "fixed"
                }
              }
            ]
          },
          {
            "matcher": {
              "id": "byName",
              "options": "HTTP Status 304"
            },
            "properties": [
              {
                "id": "color",
                "value": {
                  "fixedColor": "semi-dark-blue",
                  "mode": "fixed"
                }
              }
            ]
          }
        ]
      },
      "gridPos": {
        "h": 9,
        "w": 9,
        "x": 7,
        "y": 19
      },
      "id": 2,
      "interval": "30s",
      "options": {
        "legend": {
          "calcs": [],
          "displayMode": "list",
          "placement": "bottom",
          "showLegend": true
        },
        "tooltip": {
          "mode": "single",
          "sort": "none"
        }
      },
      "pluginVersion": "10.4.0",
      "targets": [
        {
          "datasource": {
            "type": "loki",
            "uid": "cdgce71h6yz28c"
          },
          "editorMode": "builder",
          "expr": "sum by(status) (count_over_time({job=\"fluentbit\"} | json | __error__=`` [$__auto]))",
          "legendFormat": "HTTP Status {{status}}",
          "queryType": "range",
          "refId": "A"
        }
      ],
      "title": "HTTP requests",
      "transformations": [
        {
          "id": "filterFieldsByName",
          "options": {
            "include": {
              "names": [
                "Time",
                "HTTP Status 200",
                "HTTP Status 301",
                "HTTP Status 304",
                "HTTP Status 404",
                "HTTP Status 406",
                "HTTP Status 500"
              ]
            }
          }
        }
      ],
      "type": "timeseries"
    },
    {
      "datasource": {
        "type": "loki",
        "uid": "cdgce71h6yz28c"
      },
      "description": "",
      "fieldConfig": {
        "defaults": {
          "color": {
            "mode": "palette-classic"
          },
          "custom": {
            "axisBorderShow": false,
            "axisCenteredZero": false,
            "axisColorMode": "text",
            "axisLabel": "",
            "axisPlacement": "auto",
            "barAlignment": 0,
            "drawStyle": "line",
            "fillOpacity": 100,
            "gradientMode": "hue",
            "hideFrom": {
              "legend": false,
              "tooltip": false,
              "viz": false
            },
            "insertNulls": false,
            "lineInterpolation": "smooth",
            "lineStyle": {
              "fill": "solid"
            },
            "lineWidth": 1,
            "pointSize": 5,
            "scaleDistribution": {
              "type": "linear"
            },
            "showPoints": "never",
            "spanNulls": false,
            "stacking": {
              "group": "A",
              "mode": "none"
            },
            "thresholdsStyle": {
              "mode": "off"
            }
          },
          "fieldMinMax": false,
          "mappings": [],
          "thresholds": {
            "mode": "absolute",
            "steps": [
              {
                "color": "green",
                "value": null
              },
              {
                "color": "red",
                "value": 80
              }
            ]
          },
          "unit": "decbytes"
        },
        "overrides": [
          {
            "matcher": {
              "id": "byName",
              "options": "Bytes sent"
            },
            "properties": [
              {
                "id": "color",
                "value": {
                  "fixedColor": "light-blue",
                  "mode": "fixed"
                }
              }
            ]
          }
        ]
      },
      "gridPos": {
        "h": 9,
        "w": 8,
        "x": 16,
        "y": 19
      },
      "id": 9,
      "interval": "30s",
      "options": {
        "legend": {
          "calcs": [],
          "displayMode": "list",
          "placement": "bottom",
          "showLegend": true
        },
        "tooltip": {
          "mode": "single",
          "sort": "none"
        }
      },
      "pluginVersion": "10.4.0",
      "targets": [
        {
          "datasource": {
            "type": "loki",
            "uid": "cdgce71h6yz28c"
          },
          "editorMode": "builder",
          "expr": "sum by(job) (sum_over_time({job=\"fluentbit\"} | json status, body_bytes_sent | status = `200` | unwrap body_bytes_sent | __error__=`` [$__auto]))",
          "legendFormat": "Bytes sent",
          "queryType": "range",
          "refId": "A"
        }
      ],
      "title": "Bytes Sent",
      "type": "timeseries"
    },
    {
      "collapsed": false,
      "datasource": {
        "type": "loki",
        "uid": "cdgce71h6yz28c"
      },
      "gridPos": {
        "h": 1,
        "w": 24,
        "x": 0,
        "y": 28
      },
      "id": 28,
      "panels": [],
      "targets": [
        {
          "datasource": {
            "type": "loki",
            "uid": "cdgce71h6yz28c"
          },
          "refId": "A"
        }
      ],
      "title": "Acquisition and Behaviour",
      "type": "row"
    },
    {
      "datasource": {
        "type": "loki",
        "uid": "cdgce71h6yz28c"
      },
      "description": "",
      "fieldConfig": {
        "defaults": {
          "custom": {
            "align": "auto",
            "cellOptions": {
              "type": "auto"
            },
            "filterable": false,
            "inspect": false
          },
          "mappings": [],
          "thresholds": {
            "mode": "absolute",
            "steps": [
              {
                "color": "green",
                "value": null
              },
              {
                "color": "red",
                "value": 80
              }
            ]
          }
        },
        "overrides": [
          {
            "matcher": {
              "id": "byName",
              "options": "Requests"
            },
            "properties": [
              {
                "id": "custom.width",
                "value": 300
              },
              {
                "id": "custom.cellOptions",
                "value": {
                  "mode": "gradient",
                  "type": "gauge"
                }
              },
              {
                "id": "color",
                "value": {
                  "mode": "continuous-BlPu"
                }
              }
            ]
          }
        ]
      },
      "gridPos": {
        "h": 6,
        "w": 13,
        "x": 0,
        "y": 29
      },
      "id": 7,
      "interval": "1h",
      "options": {
        "cellHeight": "sm",
        "footer": {
          "countRows": false,
          "fields": "",
          "reducer": [
            "sum"
          ],
          "show": false
        },
        "showHeader": true,
        "sortBy": [
          {
            "desc": true,
            "displayName": "Count"
          }
        ]
      },
      "pluginVersion": "10.4.0",
      "targets": [
        {
          "datasource": {
            "type": "loki",
            "uid": "cdgce71h6yz28c"
          },
          "editorMode": "builder",
          "expr": "topk(10, sum by(http_user_agent) (count_over_time({job=\"fluentbit\"} | json http_user_agent | __error__=`` [$__auto])))",
          "legendFormat": "{{agent}}",
          "queryType": "instant",
          "refId": "A"
        }
      ],
      "timeFrom": "1h",
      "title": "Top User Agents",
      "transformations": [
        {
          "id": "reduce",
          "options": {
            "labelsToFields": true,
            "reducers": []
          }
        },
        {
          "id": "organize",
          "options": {
            "excludeByName": {
              "Field": false,
              "Time": true
            },
            "includeByName": {},
            "indexByName": {},
            "renameByName": {
              "Field": "Agent",
              "Total": "Requests",
              "Value #A": "Count",
              "agent": "User Agent"
            }
          }
        }
      ],
      "type": "table"
    },
    {
      "datasource": {
        "type": "loki",
        "uid": "cdgce71h6yz28c"
      },
      "description": "Referer when it's not blank",
      "fieldConfig": {
        "defaults": {
          "custom": {
            "align": "auto",
            "cellOptions": {
              "type": "auto"
            },
            "filterable": false,
            "inspect": false
          },
          "mappings": [],
          "thresholds": {
            "mode": "absolute",
            "steps": [
              {
                "color": "green",
                "value": null
              },
              {
                "color": "red",
                "value": 80
              }
            ]
          }
        },
        "overrides": [
          {
            "matcher": {
              "id": "byName",
              "options": "Requests"
            },
            "properties": [
              {
                "id": "custom.width",
                "value": 300
              },
              {
                "id": "custom.cellOptions",
                "value": {
                  "mode": "gradient",
                  "type": "gauge"
                }
              },
              {
                "id": "color",
                "value": {
                  "mode": "continuous-BlPu"
                }
              }
            ]
          }
        ]
      },
      "gridPos": {
        "h": 6,
        "w": 11,
        "x": 13,
        "y": 29
      },
      "id": 6,
      "interval": "1h",
      "options": {
        "cellHeight": "sm",
        "footer": {
          "countRows": false,
          "fields": "",
          "reducer": [
            "sum"
          ],
          "show": false
        },
        "showHeader": true,
        "sortBy": [
          {
            "desc": true,
            "displayName": "Requests"
          }
        ]
      },
      "pluginVersion": "10.4.0",
      "targets": [
        {
          "datasource": {
            "type": "loki",
            "uid": "cdgce71h6yz28c"
          },
          "editorMode": "builder",
          "expr": "topk(20, sum by(http_referer) (count_over_time({job=\"fluentbit\"} | json | http_referer != `` | __error__=`` [$__auto])))",
          "legendFormat": "{{referer}}",
          "queryType": "instant",
          "refId": "A"
        }
      ],
      "timeFrom": "1h",
      "title": "Top HTTP Referers",
      "transformations": [
        {
          "id": "reduce",
          "options": {
            "reducers": []
          }
        },
        {
          "id": "organize",
          "options": {
            "excludeByName": {
              "Time": true
            },
            "includeByName": {},
            "indexByName": {},
            "renameByName": {
              "Field": "Referer",
              "Total": "Requests",
              "Value #A": "Requests",
              "referer": "Referer"
            }
          }
        }
      ],
      "type": "table"
    },
    {
      "datasource": {
        "type": "loki",
        "uid": "cdgce71h6yz28c"
      },
      "description": "",
      "fieldConfig": {
        "defaults": {
          "custom": {
            "align": "auto",
            "cellOptions": {
              "type": "auto"
            },
            "filterable": false,
            "inspect": false
          },
          "mappings": [],
          "thresholds": {
            "mode": "absolute",
            "steps": [
              {
                "color": "green",
                "value": null
              },
              {
                "color": "red",
                "value": 80
              }
            ]
          }
        },
        "overrides": [
          {
            "matcher": {
              "id": "byName",
              "options": "Requests"
            },
            "properties": [
              {
                "id": "custom.width",
                "value": 300
              },
              {
                "id": "custom.cellOptions",
                "value": {
                  "mode": "gradient",
                  "type": "gauge"
                }
              },
              {
                "id": "color",
                "value": {
                  "mode": "continuous-BlPu"
                }
              }
            ]
          }
        ]
      },
      "gridPos": {
        "h": 8,
        "w": 9,
        "x": 0,
        "y": 35
      },
      "id": 3,
      "interval": "30m",
      "options": {
        "cellHeight": "sm",
        "footer": {
          "countRows": false,
          "fields": "",
          "reducer": [
            "sum"
          ],
          "show": false
        },
        "showHeader": true,
        "sortBy": [
          {
            "desc": true,
            "displayName": "Requests"
          }
        ]
      },
      "pluginVersion": "10.4.0",
      "targets": [
        {
          "datasource": {
            "type": "loki",
            "uid": "cdgce71h6yz28c"
          },
          "editorMode": "builder",
          "expr": "topk(10, sum by(http_x_forwarded_for) (count_over_time({job=\"fluentbit\"} | json | __error__=`` [$__auto])))",
          "legendFormat": "{{http_x_forwarded_for}}",
          "queryType": "instant",
          "refId": "A"
        }
      ],
      "timeFrom": "1h",
      "title": "Top IPs",
      "transformations": [
        {
          "id": "reduce",
          "options": {
            "labelsToFields": true,
            "reducers": []
          }
        },
        {
          "id": "organize",
          "options": {
            "excludeByName": {
              "Field": false,
              "Time": true
            },
            "includeByName": {},
            "indexByName": {},
            "renameByName": {
              "Field": "IP Address",
              "Total": "Requests",
              "Value #A": "Requests",
              "forwardedFor": "IP Address",
              "http_x_forwarded_for": "Remote IP"
            }
          }
        }
      ],
      "type": "table"
    },
    {
      "datasource": {
        "type": "loki",
        "uid": "cdgce71h6yz28c"
      },
      "description": "",
      "fieldConfig": {
        "defaults": {
          "custom": {
            "align": "auto",
            "cellOptions": {
              "type": "auto"
            },
            "filterable": false,
            "inspect": false
          },
          "mappings": [],
          "thresholds": {
            "mode": "absolute",
            "steps": [
              {
                "color": "green",
                "value": null
              },
              {
                "color": "red",
                "value": 80
              }
            ]
          }
        },
        "overrides": [
          {
            "matcher": {
              "id": "byName",
              "options": "Total"
            },
            "properties": [
              {
                "id": "custom.width",
                "value": 300
              },
              {
                "id": "custom.cellOptions",
                "value": {
                  "mode": "gradient",
                  "type": "gauge"
                }
              },
              {
                "id": "color",
                "value": {
                  "mode": "continuous-BlPu"
                }
              }
            ]
          }
        ]
      },
      "gridPos": {
        "h": 8,
        "w": 15,
        "x": 9,
        "y": 35
      },
      "id": 12,
      "interval": "5m",
      "options": {
        "cellHeight": "sm",
        "footer": {
          "countRows": false,
          "fields": "",
          "reducer": [
            "sum"
          ],
          "show": false
        },
        "showHeader": true,
        "sortBy": [
          {
            "desc": true,
            "displayName": "Total"
          }
        ]
      },
      "pluginVersion": "10.4.0",
      "targets": [
        {
          "datasource": {
            "type": "loki",
            "uid": "cdgce71h6yz28c"
          },
          "editorMode": "builder",
          "expr": "topk(10, sum by(request_uri) (count_over_time({job=\"fluentbit\"} | json request_uri | request_uri != `/` | __error__=`` [$__auto])))",
          "legendFormat": "{{path}}",
          "queryType": "instant",
          "refId": "A"
        }
      ],
      "timeFrom": "1h",
      "title": "Top Requested Pages",
      "transformations": [
        {
          "id": "reduce",
          "options": {
            "reducers": []
          }
        },
        {
          "id": "organize",
          "options": {
            "excludeByName": {
              "Time": true
            },
            "includeByName": {},
            "indexByName": {},
            "renameByName": {
              "Field": "Page",
              "Total": "",
              "Value #A": "Total",
              "path": "Page"
            }
          }
        }
      ],
      "type": "table"
    }
  ],
  "refresh": "5m",
  "schemaVersion": 39,
  "tags": [],
  "templating": {
    "list": [
      {
        "current": {
          "selected": false,
          "text": "fluentbit",
          "value": "fluentbit"
        },
        "datasource": {
          "type": "loki",
          "uid": "cdgce71h6yz28c"
        },
        "definition": "label_values({job=\"fluentbit\"}, job)",
        "hide": 0,
        "includeAll": false,
        "label": "job",
        "multi": false,
        "name": "job",
        "options": [],
        "query": "label_values({job=\"fluentbit\"}, job)",
        "refresh": 1,
        "regex": "",
        "skipUrlSync": false,
        "sort": 0,
        "tagValuesQuery": "",
        "tagsQuery": "",
        "type": "query",
        "useTags": false
      }
    ]
  },
  "time": {
    "from": "now-1h",
    "to": "now"
  },
  "timepicker": {
    "refresh_intervals": [
      "10s",
      "30s",
      "1m",
      "5m",
      "15m",
      "30m",
      "1h",
      "2h",
      "1d"
    ]
  },
  "timezone": "",
  "title": "Loki v2 Web Analytics Dashboard for NGINX For Image Caching",
  "uid": "Nz6kKgtGk",
  "version": 11,
  "weekStart": ""
}